LICENSE
MANIFEST.in
README.md
setup.cfg
setup.py
embml/__init__.py
embml/embml.py
embml/embmlSklearn.py
embml/embmlWeka.py
embml.egg-info/PKG-INFO
embml.egg-info/SOURCES.txt
embml.egg-info/dependency_links.txt
embml.egg-info/requires.txt
embml.egg-info/top_level.txt
embml/sklearnModels/__init__.py
embml/sklearnModels/embml_sklearn_DecisionTreeClassifier.py
embml/sklearnModels/embml_sklearn_LinearSVC.py
embml/sklearnModels/embml_sklearn_LogisticRegression.py
embml/sklearnModels/embml_sklearn_MLPClassifier.py
embml/sklearnModels/embml_sklearn_SVC_Kernel.py
embml/utils/__init__.py
embml/utils/utils.py
embml/wekaModels/__init__.py
embml/wekaModels/embml_weka_J48.py
embml/wekaModels/embml_weka_Logistic.py
embml/wekaModels/embml_weka_MultilayerPerceptron.py
embml/wekaModels/embml_weka_SMO_LinearKernel.py
embml/wekaModels/embml_weka_SMO_PolyKernel.py
embml/wekaModels/embml_weka_SMO_RBFKernel.py