Metadata-Version: 2.1
Name: embml
Version: 0.0.5
Summary: A tool to support using classification models in low-power microcontroller-based hardware
Home-page: https://github.com/lucastsutsui/embml
Author: Lucas Tsutsui da Silva
Author-email: lucastsui@hotmail.com
License: GPL3
Keywords: weka,scikit-learn,microcontroller,classifier,embedded
Platform: UNKNOWN
Classifier: Programming Language :: Python :: 2.7
Classifier: Programming Language :: Python :: 3.7
Classifier: License :: OSI Approved :: GNU General Public License v3 (GPLv3)
Classifier: Operating System :: OS Independent
Requires-Python: >=2.7
